{
  "data": {
    "article": {},
    "attachments": {},
    "author_id": "1757603703811371008",
    "conversation_id": "2045034384559099921",
    "created_at": "2026-04-17T14:44:35.000Z",
    "edit_controls": {
      "editable_until": "2026-04-17T15:44:35.000Z",
      "edits_remaining": 5,
      "is_edit_eligible": false
    },
    "edit_history_tweet_ids": [
      "2045151440730292412"
    ],
    "entities": {
      "mentions": [
        {
          "end": 16,
          "id": "1684269091849404416",
          "start": 0,
          "username": "hg3551019177402"
        }
      ]
    },
    "geo": {},
    "id": "2045151440730292412",
    "in_reply_to_user_id": "1684269091849404416",
    "lang": "zh",
    "note_tweet": {
      "entities": {}
    },
    "possibly_sensitive": false,
    "public_metrics": {
      "bookmark_count": 0,
      "impression_count": 0,
      "like_count": 0,
      "quote_count": 0,
      "reply_count": 0,
      "retweet_count": 0
    },
    "referenced_tweets": [
      {
        "id": "2045034384559099921",
        "type": "replied_to"
      }
    ],
    "reply_settings": "everyone",
    "text": "@hg3551019177402 我笑得肚子疼"
  },
  "includes": {
    "media": [
      {
        "height": 2048,
        "media_key": "3_2045034371485433856",
        "public_metrics": {},
        "type": "photo",
        "url": "https://pbs.twimg.com/media/HGFr7QHagAA0T9k.jpg",
        "width": 1536
      }
    ],
    "tweets": [
      {
        "article": {},
        "attachments": {},
        "author_id": "1757603703811371008",
        "conversation_id": "2045034384559099921",
        "created_at": "2026-04-17T14:44:35.000Z",
        "edit_controls": {
          "editable_until": "2026-04-17T15:44:35.000Z",
          "edits_remaining": 5,
          "is_edit_eligible": false
        },
        "edit_history_tweet_ids": [
          "2045151440730292412"
        ],
        "entities": {
          "mentions": [
            {
              "end": 16,
              "id": "1684269091849404416",
              "start": 0,
              "username": "hg3551019177402"
            }
          ]
        },
        "geo": {},
        "id": "2045151440730292412",
        "in_reply_to_user_id": "1684269091849404416",
        "lang": "zh",
        "note_tweet": {
          "entities": {}
        },
        "possibly_sensitive": false,
        "public_metrics": {
          "bookmark_count": 0,
          "impression_count": 0,
          "like_count": 0,
          "quote_count": 0,
          "reply_count": 0,
          "retweet_count": 0
        },
        "referenced_tweets": [
          {
            "id": "2045034384559099921",
            "type": "replied_to"
          }
        ],
        "reply_settings": "everyone",
        "text": "@hg3551019177402 我笑得肚子疼"
      },
      {
        "article": {},
        "attachments": {
          "media_keys": [
            "3_2045034371485433856"
          ]
        },
        "author_id": "1684269091849404416",
        "conversation_id": "2045034384559099921",
        "created_at": "2026-04-17T06:59:26.000Z",
        "edit_controls": {
          "editable_until": "2026-04-17T07:59:26.000Z",
          "edits_remaining": 5,
          "is_edit_eligible": false
        },
        "edit_history_tweet_ids": [
          "2045034384559099921"
        ],
        "entities": {
          "urls": [
            {
              "display_url": "pic.x.com/w8cldEvMHg",
              "end": 43,
              "expanded_url": "https://x.com/hg3551019177402/status/2045034384559099921/photo/1",
              "media_key": "3_2045034371485433856",
              "start": 20,
              "url": "https://t.co/w8cldEvMHg"
            }
          ]
        },
        "geo": {},
        "id": "2045034384559099921",
        "lang": "zh",
        "note_tweet": {
          "entities": {}
        },
        "possibly_sensitive": false,
        "public_metrics": {
          "bookmark_count": 0,
          "impression_count": 374,
          "like_count": 22,
          "quote_count": 0,
          "reply_count": 6,
          "retweet_count": 0
        },
        "reply_settings": "everyone",
        "text": "看看麻木的世界\n是否依然孤独的转个不停 https://t.co/w8cldEvMHg"
      }
    ],
    "users": [
      {
        "created_at": "2024-02-14T03:12:45.000Z",
        "description": "我什么也没做错 一直被伤害 前世@xiaoyi080 友跨 偶尔打钱 爱你们",
        "entities": {
          "description": {
            "mentions": [
              {
                "end": 26,
                "start": 16,
                "username": "xiaoyi080"
              }
            ]
          }
        },
        "id": "1757603703811371008",
        "name": "11",
        "pinned_tweet_id": "2043381951839781147",
        "profile_image_url": "https://pbs.twimg.com/profile_images/2043146436347613185/S_9YQ-s3_normal.jpg",
        "protected": false,
        "public_metrics": {
          "followers_count": 89,
          "following_count": 88,
          "like_count": 19,
          "listed_count": 0,
          "media_count": 18,
          "tweet_count": 161
        },
        "username": "SonjaTasha26957",
        "verified": false
      },
      {
        "created_at": "2023-07-26T18:27:14.000Z",
        "description": "黑圣徒和白罪女 我主人@Orion2588 药物治疗精神病中（每天吃很多就是了），每天直播一下精神病日常，我的语言自知门里下贱20万bei。黑色柳丁：@rinii165892",
        "entities": {
          "description": {
            "mentions": [
              {
                "end": 21,
                "start": 11,
                "username": "Orion2588"
              },
              {
                "end": 87,
                "start": 75,
                "username": "rinii165892"
              }
            ]
          }
        },
        "id": "1684269091849404416",
        "name": "12",
        "pinned_tweet_id": "2043934459041645045",
        "profile_image_url": "https://pbs.twimg.com/profile_images/2039346571276656640/qD2Kl3Xn_normal.jpg",
        "protected": false,
        "public_metrics": {
          "followers_count": 570,
          "following_count": 541,
          "like_count": 18555,
          "listed_count": 0,
          "media_count": 481,
          "tweet_count": 8439
        },
        "username": "hg3551019177402",
        "verified": false
      }
    ]
  }
}